pelican-4.10.2.dist-info/METADATA
pelican-4.10.2.dist-info/WHEEL
pelican-4.10.2.dist-info/entry_points.txt
pelican-4.10.2.dist-info/licenses/LICENSE
pelican/__init__.py
pelican/__main__.py
pelican/cache.py
pelican/contents.py
pelican/generators.py
pelican/log.py
pelican/paginator.py
pelican/plugins/_utils.py
pelican/plugins/signals.py
pelican/readers.py
pelican/rstdirectives.py
pelican/server.py
pelican/settings.py
pelican/signals.py
pelican/tests/TestPages/bad_page.rst
pelican/tests/TestPages/draft_page.rst
pelican/tests/TestPages/draft_page_markdown.md
pelican/tests/TestPages/draft_page_with_template.rst
pelican/tests/TestPages/hidden_page.rst
pelican/tests/TestPages/hidden_page_markdown.md
pelican/tests/TestPages/hidden_page_with_template.rst
pelican/tests/TestPages/page.rst
pelican/tests/TestPages/page_markdown.md
pelican/tests/TestPages/page_used_for_sorting_test.rst
pelican/tests/TestPages/page_with_category_and_tag_links.md
pelican/tests/TestPages/page_with_static_links.md
pelican/tests/TestPages/page_with_template.rst
pelican/tests/__init__.py
pelican/tests/build_test/conftest.py
pelican/tests/build_test/test_build_files.py
pelican/tests/content/2012-11-29_rst_w_filename_meta#foo-bar.rst
pelican/tests/content/2012-11-30_md_w_filename_meta#foo-bar.md
pelican/tests/content/TestCategory/article_with_category.rst
pelican/tests/content/TestCategory/article_without_category.rst
pelican/tests/content/article.rst
pelican/tests/content/article_draft.md
pelican/tests/content/article_hidden.md
pelican/tests/content/article_skip.md
pelican/tests/content/article_with_attributes_containing_double_quotes.html
pelican/tests/content/article_with_capitalized_metadata.rst
pelican/tests/content/article_with_code_block.rst
pelican/tests/content/article_with_comments.html
pelican/tests/content/article_with_duplicate_tags_authors.md
pelican/tests/content/article_with_inline_svg.html
pelican/tests/content/article_with_keywords.html
pelican/tests/content/article_with_markdown_and_empty_tags.md
pelican/tests/content/article_with_markdown_and_footnote.md
pelican/tests/content/article_with_markdown_and_nested_metadata.md
pelican-4.10.2.dist-info/RECORD
