Metadata-Version: 2.1
Name: pelican
Version: 4.10.2
Summary: Static site generator supporting Markdown and reStructuredText
Keywords: static site generator,static sites,ssg
Author-Email: Justin Mayer <authors@getpelican.com>
License: AGPLv3
Classifier: Development Status :: 5 - Production/Stable
Classifier: Environment :: Console
Classifier: Framework :: Pelican
Classifier: Intended Audience :: End Users/Desktop
Classifier: License :: OSI Approved :: GNU Affero General Public License v3 or later (AGPLv3+)
Classifier: Operating System :: OS Independent
Classifier: Programming Language :: Python :: 3
Classifier: Programming Language :: Python :: 3.8
Classifier: Programming Language :: Python :: 3.9
Classifier: Programming Language :: Python :: 3.10
Classifier: Programming Language :: Python :: 3.11
Classifier: Programming Language :: Python :: 3.12
Classifier: Programming Language :: Python :: Implementation :: CPython
Classifier: Topic :: Internet :: WWW/HTTP :: Dynamic Content :: Content Management System
Classifier: Topic :: Internet :: WWW/HTTP :: Site Management
Classifier: Topic :: Software Development :: Libraries :: Python Modules
Classifier: Topic :: Text Processing :: Markup :: Markdown
Classifier: Topic :: Text Processing :: Markup :: HTML
Classifier: Topic :: Text Processing :: Markup :: reStructuredText
Project-URL: Homepage, https://getpelican.com
Project-URL: Funding, https://donate.getpelican.com/
Project-URL: Issue Tracker, https://github.com/getpelican/pelican/issues
Project-URL: Repository, https://github.com/getpelican/pelican
Project-URL: Documentation, https://docs.getpelican.com
Requires-Python: <4.0,>=3.8.1
Requires-Dist: blinker>=1.7.0
Requires-Dist: docutils>=0.20.1
Requires-Dist: feedgenerator>=2.1.0
Requires-Dist: jinja2>=3.1.2
Requires-Dist: ordered-set>=4.1.0
Requires-Dist: pygments>=2.16.1
Requires-Dist: python-dateutil>=2.8.2
Requires-Dist: rich>=13.6.0
Requires-Dist: unidecode>=1.3.7
Requires-Dist: backports-zoneinfo>=0.2.1; python_version < "3.9"
Requires-Dist: watchfiles>=0.21.0
Requires-Dist: tzdata; sys_platform == "win32"
Provides-Extra: markdown
Requires-Dist: markdown>=3.1; extra == "markdown"
